[
    {
        "slug": "animal-collective",
        "title": "animal collective"
    },
    {
        "slug": "k-swift",
        "title": "k swift"
    },
    {
        "slug": "rod-lee",
        "title": "Rod Lee"
    },
    {
        "slug": "james-nasty",
        "title": "James Nasty"
    },
    {
        "slug": "chris-brooks",
        "title": "Chris Brooks"
    },
    {
        "slug": "dj-technics",
        "title": "DJ Technics"
    },
    {
        "slug": "dj-booman",
        "title": "DJ Booman"
    },
    {
        "slug": "k-life",
        "title": "K‑Life"
    },
    {
        "slug": "kw-griff",
        "title": "KW Griff"
    },
    {
        "slug": "basement-boys",
        "title": "Basement Boys"
    },
    {
        "slug": "karizma",
        "title": "Karizma"
    },
    {
        "slug": "frank-ski",
        "title": "Frank Ski"
    },
    {
        "slug": "scottie-b",
        "title": "Scottie B"
    },
    {
        "slug": "dj-class",
        "title": "DJ Class"
    },
    {
        "slug": "big-ria",
        "title": "Big Ria"
    },
    {
        "slug": "tt-the-artist",
        "title": "TT The Artist"
    },
    {
        "slug": "blaqstarr",
        "title": "Blaqstarr"
    },
    {
        "slug": "cex",
        "title": "Cex"
    },
    {
        "slug": "dj-bump",
        "title": "DJ Bump"
    },
    {
        "slug": "dj-jonny-blaze",
        "title": "DJ Jonny Blaze"
    },
    {
        "slug": "porkchop",
        "title": "Porkchop"
    },
    {
        "slug": "shawn-ceasar",
        "title": "Shawn Ceasar"
    },
    {
        "slug": "ducky",
        "title": "Ducky"
    },
    {
        "slug": "shawn-smallwood",
        "title": "Shawn Smallwood"
    },
    {
        "slug": "schwarz",
        "title": "Schwarz"
    },
    {
        "slug": "calvo",
        "title": "Calvo"
    },
    {
        "slug": "kade",
        "title": "Kade"
    },
    {
        "slug": "dj-patrick",
        "title": "Dj Patrick"
    },
    {
        "slug": "scott-henry",
        "title": "Scott Henry"
    },
    {
        "slug": "dj-who",
        "title": "Dj Who"
    },
    {
        "slug": "glitch",
        "title": "Glitch"
    },
    {
        "slug": "charles-feelgood",
        "title": "Charles Feelgood"
    },
    {
        "slug": "depth-perception",
        "title": "depth perception"
    },
    {
        "slug": "lonnie-fisher",
        "title": "Lonnie Fisher"
    },
    {
        "slug": "cullen-stalin",
        "title": "Cullen Stalin"
    },
    {
        "slug": "paradox",
        "title": "paradox"
    },
    {
        "slug": "the-crown",
        "title": "The Crown"
    },
    {
        "slug": "the-red-maple",
        "title": "The Red Maple"
    },
    {
        "slug": "sonar",
        "title": "Sonar"
    },
    {
        "slug": "talking-head",
        "title": "Talking Head"
    },
    {
        "slug": "1722",
        "title": "1722"
    },
    {
        "slug": "cignal",
        "title": "Cignal"
    },
    {
        "slug": "the-compound",
        "title": "the compound"
    },
    {
        "slug": "mace-st-warehouse",
        "title": "Mace St Warehouse"
    },
    {
        "slug": "graffiti-warehouse",
        "title": "Graffiti Warehouse"
    },
    {
        "slug": "floristree",
        "title": "Floristree"
    },
    {
        "slug": "unruly-records",
        "title": "Unruly Records"
    },
    {
        "slug": "defective-records",
        "title": "Defective Records"
    },
    {
        "slug": "gargoyle-records",
        "title": "Gargoyle Records"
    },
    {
        "slug": "klub-kings",
        "title": "Klub Kings"
    },
    {
        "slug": "baltimore-breakbeats",
        "title": "Baltimore Breakbeats"
    },
    {
        "slug": "ear-4-music",
        "title": "Ear 4 Music"
    },
    {
        "slug": "quit-records",
        "title": "Quit Records"
    },
    {
        "slug": "poji-records",
        "title": "Poji Records"
    },
    {
        "slug": "pimp-house-records",
        "title": "Pimp House Records"
    },
    {
        "slug": "deco-records",
        "title": "Deco Records"
    },
    {
        "slug": "king-of-klub",
        "title": "King Of Klub"
    },
    {
        "slug": "code-red",
        "title": "Code Red"
    },
    {
        "slug": "pirate-brain",
        "title": "Pirate brain"
    },
    {
        "slug": "e2e4",
        "title": "E2e4"
    },
    {
        "slug": "dimensions-in-music",
        "title": "Dimensions in Music"
    },
    {
        "slug": "mount-vernon-records",
        "title": "Mount Vernon Records"
    },
    {
        "slug": "music-liberated",
        "title": "Music Liberated"
    },
    {
        "slug": "sound-of-baltimore",
        "title": "Sound of Baltimore"
    },
    {
        "slug": "inner-city-records",
        "title": "Inner City Records"
    },
    {
        "slug": "metro-stereo",
        "title": "Metro Stereo"
    },
    {
        "slug": "clubs",
        "title": "Clubs"
    },
    {
        "slug": "flyers",
        "title": "Flyers"
    },
    {
        "slug": "studio",
        "title": "Studio"
    },
    {
        "slug": "parties",
        "title": "Parties"
    },
    {
        "slug": "enock",
        "title": "Enock"
    },
    {
        "slug": "booda-monk",
        "title": "Booda Monk"
    },
    {
        "slug": "noodles",
        "title": "Noodles"
    },
    {
        "slug": "house-of-revlon",
        "title": "House of Revlon"
    },
    {
        "slug": "tsu-dance-crew",
        "title": "TSU Dance Crew"
    },
    {
        "slug": "tsr-dance-crew",
        "title": "TSR Dance Crew"
    },
    {
        "slug": "deadly-venom-breakdance-crew",
        "title": "Deadly Venom Breakdance Crew"
    }
]